apschedulerui/__init__.py
apschedulerui/watcher.py
apschedulerui/web.py
apschedulerui/static/app.bundle.js
apschedulerui/static/index.html
apschedulerui-0.0.1.dist-info/LICENSE.txt
apschedulerui-0.0.1.dist-info/METADATA
apschedulerui-0.0.1.dist-info/WHEEL
apschedulerui-0.0.1.dist-info/top_level.txt
apschedulerui-0.0.1.dist-info/RECORD
