Metadata-Version: 2.1
Name: apschedulerui
Version: 0.0.1
Summary: UNKNOWN
Home-page: https://github.com/schmidtfederico/apscheduler-ui
Author: Federico Schmidt
Author-email: schmidt.fdr@gmail.com
License: UNKNOWN
Platform: UNKNOWN
Classifier: Development Status :: 3 - Alpha
Classifier: Intended Audience :: Developers
Classifier: License :: OSI Approved :: MIT License
Classifier: Programming Language :: Python
Classifier: Programming Language :: Python :: 3
Classifier: Programming Language :: Python :: 3.5
Classifier: Programming Language :: Python :: 3.6
Classifier: Programming Language :: Python :: 3.7
Classifier: Operating System :: OS Independent
Classifier: Topic :: Internet
Requires-Python: >=3.5, <4
Requires-Dist: apscheduler (>=3.0.0)
Requires-Dist: flask (>=1.0.0)
Requires-Dist: flask-socketio (>=4.0.0)
Provides-Extra: testing
Requires-Dist: requests ; extra == 'testing'
Requires-Dist: mock ; (python_version == "3.5") and extra == 'testing'
